{"performances": [{"events": {"start": [{"v": 34, "uid": 7280900822034, "sid": 8220}, {"v": 145, "uid": 72809008221145, "sid": 8221}], "end": []}, "time": "2014-07-28T09:00:00"}, {"events": {"start": [{"v": 176, "uid": 72810007032176, "sid": 7032}, {"v": 19, "uid": 7281000861919, "sid": 8619}, {"v": 28, "uid": 7281000701928, "sid": 7019}, {"v": 66, "uid": 7281000725366, "sid": 7253}, {"v": 222, "uid": 72810007759222, "sid": 7759}, {"v": 66, "uid": 7281000879266, "sid": 8792}, {"v": 222, "uid": 72810008793222, "sid": 8793}, {"v": 46, "uid": 7281000879446, "sid": 8794}, {"v": 46, "uid": 7281000749746, "sid": 7497}, {"v": 46, "uid": 7281000749246, "sid": 7492}, {"v": 145, "uid": 72810008224145, "sid": 8224}, {"v": 179, "uid": 72810007581179, "sid": 7581}, {"v": 179, "uid": 72810007332179, "sid": 7332}, {"v": 414, "uid": 72810008976414, "sid": 8976}, {"v": 434, "uid": 72810009827434, "sid": 9827}], "end": []}, "time": "2014-07-28T10:00:00"}, {"events": {"start": [{"v": 402, "uid": 72810307023402, "sid": 7023}], "end": []}, "time": "2014-07-28T10:30:00"}, {"events": {"start": [{"v": 129, "uid": 72812006603129, "sid": 6603}], "end": []}, "time": "2014-07-28T12:00:00"}, {"events": {"start": [], "end": [{"v": 129, "uid": 72812006603129, "sid": 6603}]}, "time": "2014-07-28T12:45:00"}, {"events": {"start": [{"v": 129, "uid": 72813006596129, "sid": 6596}], "end": []}, "time": "2014-07-28T13:00:00"}, {"events": {"start": [{"v": 129, "uid": 72814006603129, "sid": 6603}], "end": []}, "time": "2014-07-28T14:00:00"}, {"events": {"start": [], "end": [{"v": 129, "uid": 72813006596129, "sid": 6596}]}, "time": "2014-07-28T14:15:00"}, {"events": {"start": [{"v": 121, "uid": 72814307588121, "sid": 7588}], "end": []}, "time": "2014-07-28T14:30:00"}, {"events": {"start": [{"v": 178, "uid": 72814406629178, "sid": 6629}], "end": []}, "time": "2014-07-28T14:40:00"}, {"events": {"start": [], "end": [{"v": 129, "uid": 72814006603129, "sid": 6603}]}, "time": "2014-07-28T14:45:00"}, {"events": {"start": [{"v": 129, "uid": 72815006596129, "sid": 6596}], "end": []}, "time": "2014-07-28T15:00:00"}, {"events": {"start": [], "end": [{"v": 121, "uid": 72814307588121, "sid": 7588}]}, "time": "2014-07-28T15:30:00"}, {"events": {"start": [], "end": [{"v": 178, "uid": 72814406629178, "sid": 6629}]}, "time": "2014-07-28T15:40:00"}, {"events": {"start": [{"v": 129, "uid": 72816006603129, "sid": 6603}], "end": [{"v": 402, "uid": 72810307023402, "sid": 7023}]}, "time": "2014-07-28T16:00:00"}, {"events": {"start": [], "end": [{"v": 129, "uid": 72815006596129, "sid": 6596}]}, "time": "2014-07-28T16:15:00"}, {"events": {"start": [], "end": [{"v": 129, "uid": 72816006603129, "sid": 6603}]}, "time": "2014-07-28T16:45:00"}, {"events": {"start": [{"v": 356, "uid": 72817006207356, "sid": 6207}, {"v": 129, "uid": 72817006596129, "sid": 6596}], "end": [{"v": 179, "uid": 72810007581179, "sid": 7581}, {"v": 179, "uid": 72810007332179, "sid": 7332}]}, "time": "2014-07-28T17:00:00"}, {"events": {"start": [], "end": [{"v": 28, "uid": 7281000701928, "sid": 7019}]}, "time": "2014-07-28T17:45:00"}, {"events": {"start": [{"v": 129, "uid": 72818006761129, "sid": 6761}], "end": [{"v": 19, "uid": 7281000861919, "sid": 8619}, {"v": 66, "uid": 7281000725366, "sid": 7253}, {"v": 222, "uid": 72810007759222, "sid": 7759}, {"v": 66, "uid": 7281000879266, "sid": 8792}, {"v": 222, "uid": 72810008793222, "sid": 8793}, {"v": 46, "uid": 7281000879446, "sid": 8794}, {"v": 46, "uid": 7281000749746, "sid": 7497}, {"v": 46, "uid": 7281000749246, "sid": 7492}]}, "time": "2014-07-28T18:00:00"}, {"events": {"start": [], "end": [{"v": 129, "uid": 72817006596129, "sid": 6596}]}, "time": "2014-07-28T18:15:00"}, {"events": {"start": [], "end": [{"v": 356, "uid": 72817006207356, "sid": 6207}]}, "time": "2014-07-28T18:30:00"}, {"events": {"start": [{"v": 129, "uid": 72819006762129, "sid": 6762}], "end": [{"v": 176, "uid": 72810007032176, "sid": 7032}]}, "time": "2014-07-28T19:00:00"}, {"events": {"start": [], "end": [{"v": 129, "uid": 72818006761129, "sid": 6761}]}, "time": "2014-07-28T19:15:00"}, {"events": {"start": [{"v": 178, "uid": 72819307151178, "sid": 7151}], "end": []}, "time": "2014-07-28T19:30:00"}, {"events": {"start": [{"v": 129, "uid": 72820006761129, "sid": 6761}], "end": [{"v": 414, "uid": 72810008976414, "sid": 8976}]}, "time": "2014-07-28T20:00:00"}, {"events": {"start": [], "end": [{"v": 129, "uid": 72819006762129, "sid": 6762}]}, "time": "2014-07-28T20:30:00"}, {"events": {"start": [{"v": 129, "uid": 72821006762129, "sid": 6762}], "end": []}, "time": "2014-07-28T21:00:00"}, {"events": {"start": [], "end": [{"v": 129, "uid": 72820006761129, "sid": 6761}]}, "time": "2014-07-28T21:15:00"}, {"events": {"start": [], "end": [{"v": 178, "uid": 72819307151178, "sid": 7151}]}, "time": "2014-07-28T21:30:00"}, {"events": {"start": [{"v": 129, "uid": 72822006763129, "sid": 6763}], "end": [{"v": 145, "uid": 72810008224145, "sid": 8224}, {"v": 434, "uid": 72810009827434, "sid": 9827}]}, "time": "2014-07-28T22:00:00"}, {"events": {"start": [], "end": [{"v": 129, "uid": 72821006762129, "sid": 6762}]}, "time": "2014-07-28T22:30:00"}, {"events": {"start": [], "end": [{"v": 129, "uid": 72822006763129, "sid": 6763}]}, "time": "2014-07-28T23:30:00"}, {"events": {"start": [], "end": [{"v": 34, "uid": 7280900822034, "sid": 8220}, {"v": 145, "uid": 72809008221145, "sid": 8221}]}, "time": "2014-07-29T05:00:00"}], "categories": {"Exhibitions": 13, "Comedy": 1, "Events": 17, "Theatre": 1, "Children's Shows": 1}}