[{"score": 44.56, "title": "People who like Cadbury Fabulous Fingers"}, {"score": 98.82, "title": "People who like Walls Viennetta Red Berries Ice Cream"}, {"score": 21.08, "title": "People who like Suntory"}, {"score": 49.83, "title": "Fans of Jimmy Edwards"}, {"score": 98.33, "title": "Owners of an Airedale Terrier"}, {"score": 24.8, "title": "Orphan Black viewers"}, {"score": 4.2, "title": "People who like The Rover"}, {"score": 78.34, "title": "People who like Magnum Almond Sticks Ice Cream"}, {"score": 88.08, "title": "People who like Insidious: Chapter 2"}, {"score": 34.3, "title": "Fans of Daft Punk"}, {"score": 9.97, "title": "People who like Peter's Friends"}, {"score": 70.51, "title": "Customers of Caf\u00e9 Rouge"}, {"score": 89.23, "title": "People who like Tarzan"}, {"score": 11.64, "title": "People who like Vegetarian Cholent"}, {"score": 89.53, "title": "Fans of Ulster Rugby"}, {"score": 59.05, "title": "People who like Divine White Chocolate"}, {"score": 91.89, "title": "Fans of England National Rugby League Team"}, {"score": 7.08, "title": "People who like Helen Newlove"}, {"score": 73.88, "title": "Foyle's War viewers"}, {"score": 9.03, "title": "People who like The Quick and the Dead"}, {"score": 34.14, "title": "People who like The Muppets"}, {"score": 97.76, "title": "People who like Birmingham Midshires"}, {"score": 61.76, "title": "Fans of Mick Jones"}, {"score": 64.1, "title": "People who like Dirty Beasts"}, {"score": 70.36, "title": "The Lone Ranger viewers"}, {"score": 44.16, "title": "People who like Haribo Wine Gums"}, {"score": 72.07, "title": "People who like Vivitar"}, {"score": 29.32, "title": "People who visit The Spectator"}, {"score": 19.9, "title": "Fans of Larry David"}, {"score": 6.48, "title": "Fans of Jamie Cullum"}, {"score": 91.38, "title": "People who enjoy St. Leger Stakes"}, {"score": 12.87, "title": "Fans of Maisie Williams"}, {"score": 4.41, "title": "Readers of Maus II: A Survivors Tale: And Here My Troubles Began"}, {"score": 70.73, "title": "Fans of Adam Ant"}, {"score": 52.74, "title": "People who like New York Cheese Cake"}, {"score": 60.71, "title": "Fans of Denise Welch"}, {"score": 97.41, "title": "People who like Zardoz"}, {"score": 35.93, "title": "People who like Walkers Squares Salt And Vinegar"}, {"score": 88.57, "title": "People who like Denplan"}, {"score": 20.53, "title": "People who like Desperado"}, {"score": 4.2, "title": "Fans of Harry Shearer"}, {"score": 94.67, "title": "Fans of Philip Oakey"}, {"score": 62.94, "title": "People who like Maltesers White"}, {"score": 90.35, "title": "People who like Tesco Mini Poppadoms"}, {"score": 82.73, "title": "People who buy things from Boots"}, {"score": 8.45, "title": "People who like Ankara"}, {"score": 7.11, "title": "People who like Cadbury Snack"}, {"score": 80.82, "title": "People who like Dr. Loosen"}, {"score": 17.66, "title": "People who like Finnish Lapphund"}, {"score": 68.5, "title": "People who like Northern Inuit"}, {"score": 89.52, "title": "Customers of Novatech"}, {"score": 37.82, "title": "Home to Roost viewers"}, {"score": 13.29, "title": "People who like Mary Glindon"}, {"score": 14.16, "title": "People who like Baked Zucchini Flowers"}, {"score": 32.69, "title": "Fans of Alison Steadman"}, {"score": 43.21, "title": "People who like Jan van Eyck"}, {"score": 85.62, "title": "Fans of Vincent Simone"}, {"score": 7.23, "title": "People who like Cancer Research UK"}, {"score": 80.33, "title": "Readers of Susie Dent"}, {"score": 70.7, "title": "Fans of Kevin McKidd"}, {"score": 48.56, "title": "People who like M&M's Crispy"}, {"score": 68.32, "title": "People who use Greenpeople"}, {"score": 50.84, "title": "Fans of Messiah"}, {"score": 37.48, "title": "People who shop at Clinton Cards"}, {"score": 11.4, "title": "Fans of Bert Trautmann"}, {"score": 70.48, "title": "Fans of Go West"}, {"score": 25.4, "title": "Fans of Nick Nolte"}, {"score": 74.98, "title": "People who like Casino Royale"}, {"score": 21.71, "title": "Viewers of 4Music"}, {"score": 0.49, "title": "Readers of Dolores Claiborne"}, {"score": 5.96, "title": "Readers of The Sandman: Endless Nights"}, {"score": 81.09, "title": "Fans of Tears for Fears"}, {"score": 95.98, "title": "Fans of Nancy Cartwright"}, {"score": 89.19, "title": "People who own a Nokia Lumia 520"}, {"score": 18.64, "title": "People who like Clive Betts"}, {"score": 92.51, "title": "Danger Man viewers"}, {"score": 77.01, "title": "People who like The Cat Returns"}, {"score": 31.86, "title": "Readers of London - The Biography"}, {"score": 23.54, "title": "Fans of Sid Owen"}, {"score": 20.01, "title": "Penn & Teller: Bullshit! viewers"}, {"score": 85.25, "title": "Readers of Malcolm Muggeridge"}, {"score": 56.41, "title": "Customers of The Times"}, {"score": 87.1, "title": "People who like Federation of Master Builders"}, {"score": 88.03, "title": "People who like The Pied Piper of Hamelin"}, {"score": 91.78, "title": "People with an interest in Peterborough"}, {"score": 0.6, "title": "People who like Mary Warnock, Baroness Warnock"}, {"score": 3.58, "title": "People who like Schweinshaxe"}, {"score": 96.48, "title": "British people who have a special interest in Cape Verde"}, {"score": 43.28, "title": "People who like Campaign Against Honour Killing"}, {"score": 84.85, "title": "Fans of Josef Strauss"}, {"score": 49.17, "title": "Listeners of Global News"}, {"score": 90.85, "title": "Fans of Girls Aloud"}, {"score": 15.49, "title": "People who like Marrakech"}, {"score": 51.25, "title": "People who like Keith Vaz"}, {"score": 92.25, "title": "Viewers of Discovery Home & Health"}, {"score": 58.06, "title": "Fans of Gwen Stefani"}, {"score": 87.79, "title": "People who like Two Mules for Sister Sara"}, {"score": 54.67, "title": "People who like Whales"}, {"score": 87.09, "title": "Fans of Alan Jackson"}, {"score": 72.32, "title": "People who like Liquor 43"}, {"score": 83.23, "title": "Fans of Fay Ripley"}, {"score": 0.7, "title": "Fans of Steve Hughes"}, {"score": 65.76, "title": "Customers of Little Chef"}, {"score": 71.92, "title": "People who like Roast Chicken"}, {"score": 44.26, "title": "Fans of Bradford City A.F.C."}, {"score": 17.43, "title": "People who like Momo"}, {"score": 91.22, "title": "Fans of Gloucester RFC"}, {"score": 97.88, "title": "People who like Yes Man"}, {"score": 17.18, "title": "People who like French Brittany"}, {"score": 28.03, "title": "Fans of Paul Michael Glaser"}, {"score": 95.6, "title": "Fans of Brendan Coyle"}, {"score": 25.34, "title": "People who like Salmon Teriyaki"}, {"score": 36.66, "title": "Fans of John Cleese"}, {"score": 38.16, "title": "Customers of Fanta"}, {"score": 9.0, "title": "Survivors viewers"}, {"score": 18.98, "title": "People who like Iain McKenzie"}, {"score": 91.82, "title": "My Hero viewers"}, {"score": 72.68, "title": "People who like Asparagus With Bechamel Sauce"}, {"score": 44.23, "title": "People who like Rebel Without a Cause"}, {"score": 58.31, "title": "People who like Hoxton Gin"}]