[{"score": 2.38, "title": "Fans of Emeric Pressburger"}, {"score": 65.48, "title": "People who like Nestle Dairy Box"}, {"score": 20.3, "title": "Fans of Charlie Parker"}, {"score": 74.42, "title": "Viewers of Drama"}, {"score": 34.83, "title": "People who wear Merrell"}, {"score": 51.27, "title": "People who like Bournville Old Jamaica"}, {"score": 50.99, "title": "People who drink Echo Falls"}, {"score": 4.11, "title": "People with an interest in Merseyside"}, {"score": 37.91, "title": "Users of New Scientist"}, {"score": 21.69, "title": "People who like Schnitzel"}, {"score": 0.0, "title": "Readers of Fortean Times"}, {"score": 4.78, "title": "Banzai viewers"}, {"score": 19.65, "title": "Fans of Glenn Hoddle"}, {"score": 35.27, "title": "Fans of Roberta Flack"}, {"score": 47.78, "title": "Listeners of Another Case Of Milton Jones"}, {"score": 79.7, "title": "Fans of Razorlight"}, {"score": 31.64, "title": "People who like Oban"}, {"score": 82.44, "title": "Fans of Justine Henin"}, {"score": 65.11, "title": "Fans of Patrick Duffy"}, {"score": 43.91, "title": "Owners of a Scottish Terrier"}, {"score": 36.13, "title": "People who enjoy Choral singing"}, {"score": 0.85, "title": "People who like Uncle Vanya"}, {"score": 42.92, "title": "People who like Pizza Rustica"}, {"score": 15.64, "title": "Fans of Megadeth"}, {"score": 64.83, "title": "People who like Belvoir Brewery"}, {"score": 90.08, "title": "People who like The Blair Witch Project"}, {"score": 66.68, "title": "Customers of Boston Tea Party"}, {"score": 32.87, "title": "Fans of Ed Byrne"}, {"score": 60.19, "title": "People who like NASA"}, {"score": 90.5, "title": "Isle Of Man TT viewers"}, {"score": 14.39, "title": "Fans of Harry Dean Stanton"}, {"score": 47.64, "title": "Ideal viewers"}, {"score": 9.13, "title": "People who like Diples (Honey Rolls)"}, {"score": 42.15, "title": "People who describe themselves as Happy"}, {"score": 42.11, "title": "People who like *Batteries Not Included"}, {"score": 35.09, "title": "Readers of 61 Hours"}, {"score": 82.06, "title": "Fans of Michael Bubl\u00e9"}, {"score": 59.14, "title": "Readers of Dirk Gently's Holistic Detective Agency"}, {"score": 74.7, "title": "Owners of a Jack Russell Terrier"}, {"score": 96.94, "title": "Listeners of The Media Show"}, {"score": 40.73, "title": "Fans of Bj\u00f6rk"}, {"score": 26.0, "title": "Readers of The Phantom of the Opera"}, {"score": 8.33, "title": "Readers of In Cold Blood"}, {"score": 76.97, "title": "Fans of Carl Maria von Weber"}, {"score": 35.49, "title": "People who like Hawk Conservancy Trust "}, {"score": 28.28, "title": "Fans of Poppy Montgomery"}, {"score": 94.74, "title": "Conservative Party supporters"}, {"score": 78.18, "title": "Fans of The Carpenters"}, {"score": 64.33, "title": "People who like Star Trek Into Darkness"}, {"score": 15.1, "title": "People who like The Hunger Games"}, {"score": 62.77, "title": "People who like Sheltiedoodle"}, {"score": 48.14, "title": "People who like David Steel"}, {"score": 74.67, "title": "Readers of Rod Liddle"}, {"score": 15.15, "title": "Fans of The Maccabees"}, {"score": 99.07, "title": "People who like Slugs"}, {"score": 50.08, "title": "People who like Hot Cross Bun"}, {"score": 85.21, "title": "British people who have a special interest in Qatar"}, {"score": 15.01, "title": "People who like Michael Dugher"}, {"score": 33.23, "title": "Fans of Naomi Campbell"}, {"score": 38.31, "title": "People who like Turn the tide of suicide"}, {"score": 3.26, "title": "Fans of Ben Flower"}, {"score": 70.48, "title": "Readers of Book of the Dead"}, {"score": 89.99, "title": "People who like Robin Walker"}, {"score": 20.97, "title": "People who like Bryan Gould"}, {"score": 4.01, "title": "Readers of The Ringworld Engineers"}, {"score": 40.22, "title": "Fans of Martin Sheen"}, {"score": 34.75, "title": "Customers of RSA Insurance"}, {"score": 51.52, "title": "Fans of Michael Hutchence"}, {"score": 46.1, "title": "People who like Crocodile Dundee"}, {"score": 7.69, "title": "People who like Nikujaga"}, {"score": 5.98, "title": "People who like Gigi (Soundtrack)"}, {"score": 79.03, "title": "Fans of T'Pau"}, {"score": 30.59, "title": "People who like Beans on Toast"}, {"score": 15.04, "title": "Casey Jones viewers"}, {"score": 76.75, "title": "Fans of Mackenzie Crook"}, {"score": 30.84, "title": "People who like Geese"}, {"score": 67.48, "title": "Fans of Chris Langham"}, {"score": 23.32, "title": "Customers of Reed"}, {"score": 33.63, "title": "Customers of Scottish Hydro Electric"}, {"score": 20.55, "title": "People who like Pierogi (Polish Dumplings)"}, {"score": 66.55, "title": "Fans of Will.i.am"}, {"score": 38.89, "title": "Fans of Peter Hall"}, {"score": 72.15, "title": "People who use Paul Mitchell"}, {"score": 61.66, "title": "Customers of Monarch Airlines"}, {"score": 11.48, "title": "Readers of Graham Greene"}, {"score": 72.21, "title": "Fans of Xabi Alonso"}, {"score": 49.97, "title": "Country House Rescue viewers"}, {"score": 12.51, "title": "People who like Star Trek VI: The Undiscovered Country"}, {"score": 81.88, "title": "Fans of Billy Idol"}, {"score": 32.44, "title": "Customers of The Co-operative Food"}, {"score": 12.53, "title": "People who like Go Ahead Apple Bakes"}, {"score": 34.41, "title": "People who wear Mango"}, {"score": 58.87, "title": "People who like Overgate Hospice"}, {"score": 12.18, "title": "Fans of Joe Walsh"}, {"score": 26.03, "title": "People who like Scouse"}, {"score": 69.01, "title": "British people who have a special interest in Dubai"}, {"score": 89.02, "title": "Owners of a Persian cat"}, {"score": 14.13, "title": "People who like Butlins"}, {"score": 26.08, "title": "Customers of Purdey's"}, {"score": 47.54, "title": "Readers of Maya Angelou"}, {"score": 37.0, "title": "Customers of London Midland"}, {"score": 58.68, "title": "Fans of Shirley Temple"}, {"score": 72.48, "title": "People who like Hula Hoops Big Hoops BBQ Beef"}, {"score": 60.26, "title": "People who like Milk"}, {"score": 19.03, "title": "Fans of Crystal Gayle"}, {"score": 52.93, "title": "Game of Thrones viewers"}, {"score": 99.51, "title": "Readers of River God"}, {"score": 46.67, "title": "Fans of Georg Philipp Telemann"}, {"score": 32.26, "title": "People who like National Union of Students"}, {"score": 17.8, "title": "People who enjoy Yoga"}, {"score": 75.9, "title": "Poldark viewers"}, {"score": 17.5, "title": "Listeners of Edith Bowman"}, {"score": 71.97, "title": "People who like Four Seasons Hotels"}, {"score": 0.5, "title": "People who like Crombie"}, {"score": 90.19, "title": "People who like Montezumas Minted"}, {"score": 96.28, "title": "People who like Magnum Mini Liqueur Irish Cream and Lemoncello Ice Cream"}, {"score": 39.03, "title": "Fans of Nick Frost"}, {"score": 93.91, "title": "People who like Peach Cobbler"}, {"score": 10.84, "title": "Fans of Jamie Foxx"}, {"score": 36.94, "title": "People who use Always"}]