[{"score": 19.13, "title": "People who like The Importance of Being Earnest"}, {"score": 88.8, "title": "People who like The Ten Commandments"}, {"score": 95.49, "title": "Readers of Jo Nesb\u00f8"}, {"score": 78.32, "title": "Fans of Lee Marvin"}, {"score": 38.58, "title": "People who like Jelly Bones"}, {"score": 45.05, "title": "People who like Baked Potato"}, {"score": 38.79, "title": "Customers of Dell Inspiron"}, {"score": 95.17, "title": "Fans of George Peppard"}, {"score": 21.23, "title": "People who like Date and Walnut Loaf"}, {"score": 23.47, "title": "People who like Ian Davidson"}, {"score": 69.6, "title": "Fans of Ian McShane"}, {"score": 54.1, "title": "Customers of Dunlop"}, {"score": 90.26, "title": "Fans of Michael Williams"}, {"score": 15.75, "title": "People who like National Animal Welfare Trust (NAWT)"}, {"score": 3.88, "title": "People who like Water Cooked Fish"}, {"score": 14.53, "title": "Fans of Cornish Pirates"}, {"score": 52.08, "title": "People who wear Dune"}, {"score": 16.51, "title": "People who like Tortelloni"}, {"score": 41.63, "title": "People who like Masala Tea"}, {"score": 57.27, "title": "Fans of Cozy Powell"}, {"score": 74.98, "title": "People who like Nicholas Winterton"}, {"score": 82.14, "title": "People who like Elizabeth Truss"}, {"score": 1.61, "title": "People who visit New Statesman"}, {"score": 49.77, "title": "Fans of Roger Federer"}, {"score": 72.48, "title": "People who like Basic Instinct"}, {"score": 24.65, "title": "Customers of Frijj"}, {"score": 95.94, "title": "People who like Hershey's Milk Chocolate"}, {"score": 48.09, "title": "People who like Cornwall Hospice Care"}, {"score": 39.95, "title": "People who like Stracciatella Soup"}, {"score": 79.26, "title": "People who drive a Volvo"}, {"score": 80.35, "title": "Fans of Tony Pulis"}, {"score": 82.26, "title": "People who like St. Cuthbert's Hospice"}, {"score": 1.47, "title": "Readers of SuperFreakonomics"}, {"score": 64.41, "title": "People who wear Footjoy"}, {"score": 31.55, "title": "People who like A.I. Artificial Intelligence"}, {"score": 0.0, "title": "People who like Electra"}, {"score": 63.56, "title": "NYPD Blue viewers"}, {"score": 74.83, "title": "Fans of Bill Oddie"}, {"score": 32.06, "title": "People who like Tyskie"}, {"score": 82.98, "title": "Fans of Bernard Hill"}, {"score": 64.97, "title": "People who like Shrek the Third"}, {"score": 18.97, "title": "Fans of Daniel Day-Lewis"}, {"score": 84.3, "title": "Fans of Chris Martin"}, {"score": 63.39, "title": "Fans of Pharrell Williams"}, {"score": 76.68, "title": "People who like Belle De Jour"}, {"score": 31.89, "title": "People who like Fruit Dumplings"}, {"score": 84.25, "title": "People with an interest in Canterbury"}, {"score": 75.35, "title": "People who like Tuborg"}, {"score": 76.41, "title": "People who like Waffle"}, {"score": 93.14, "title": "People who use Elizabeth Arden"}, {"score": 68.74, "title": "People who like Evil Dead"}, {"score": 46.06, "title": "Fans of George Sanders"}, {"score": 69.37, "title": "People who drive a Mitsubishi"}, {"score": 96.26, "title": "People who like Llamas"}, {"score": 94.52, "title": "People who like East Lothian"}, {"score": 78.67, "title": "Readers of Nigel Dempster"}, {"score": 30.6, "title": "People who like Walkers Extra Crunchy Cheddar And Sour Cream"}, {"score": 88.73, "title": "Readers of Life and Laughing: My Story"}, {"score": 72.85, "title": "Readers of Animal Life"}, {"score": 17.92, "title": "People who use Solpadeine"}, {"score": 27.78, "title": "Listeners of I've Never Seen Star Wars"}, {"score": 9.65, "title": "People who like The Dormen Wasabi Peanuts"}, {"score": 37.0, "title": "Fans of Jessica Alba"}, {"score": 91.67, "title": "Listeners of A History of the World Special"}, {"score": 58.65, "title": "Readers of Maurice"}, {"score": 36.74, "title": "Fans of Lorraine Pascale"}, {"score": 2.07, "title": "People who like Hugh Pennington"}, {"score": 37.3, "title": "Fans of Christopher Nolan"}, {"score": 68.52, "title": "Readers of A Murder is Announced"}, {"score": 9.89, "title": "People who like Kerrygold"}, {"score": 88.03, "title": "British people who have a special interest in Bahrain"}, {"score": 58.61, "title": "Readers of Charles Darwin"}, {"score": 62.85, "title": "Readers of Mr. Midshipman Hornblower"}, {"score": 3.03, "title": "Readers of The Black Echo"}, {"score": 54.95, "title": "Users of thetrainline"}, {"score": 90.05, "title": "People who donate to NSPCC"}, {"score": 35.9, "title": "People who like Othello"}, {"score": 23.1, "title": "Supernanny viewers"}, {"score": 51.75, "title": "People who wear Aldo"}, {"score": 24.28, "title": "Fans of Claire Tomlinson"}, {"score": 41.88, "title": "People who like The Poetry of Edgar Allen Poe"}, {"score": 25.2, "title": "People who like Wilkins Cider"}, {"score": 32.65, "title": "Readers of Frenchman's Creek"}, {"score": 65.02, "title": "Customers of Gatwick Airport"}, {"score": 73.3, "title": "People who enjoy Communicating with friends and family"}, {"score": 35.21, "title": "Customers of Walkers"}, {"score": 16.48, "title": "People who like Vicky Pryce"}, {"score": 42.74, "title": "People who are interested in Environmental studies"}, {"score": 23.15, "title": "People who like UNICEF"}, {"score": 53.72, "title": "Fans of Manchester United F.C."}, {"score": 10.31, "title": "People who like Ritz Hotel"}, {"score": 46.63, "title": "Readers of Through the Looking-Glass"}, {"score": 79.64, "title": "People who like Thomas Galbraith, 2nd Baron Strathclyde"}, {"score": 19.3, "title": "People who like Fox's Triple Bar"}, {"score": 56.51, "title": "Lost viewers"}, {"score": 47.64, "title": "Fans of Liverpool F.C."}, {"score": 56.89, "title": "Readers of Adventures of Huckleberry Finn"}, {"score": 0.83, "title": "People who like Greenpeace Unfriend Coal"}, {"score": 79.95, "title": "Owners of a Norwegian Forest Cat"}, {"score": 58.69, "title": "People who like Unbreakable"}, {"score": 98.6, "title": "Fans of Mark Selby"}, {"score": 30.32, "title": "Readers of Kerrang!"}, {"score": 75.49, "title": "People who like Open Water"}, {"score": 44.27, "title": "People who like Deliverance"}, {"score": 86.47, "title": "People who like The Three Musketeers"}, {"score": 51.22, "title": "Fans of Simon Bird"}, {"score": 51.57, "title": "Fans of Susan Hayward"}, {"score": 71.54, "title": "People who like Seabiscuit"}, {"score": 24.0, "title": "People who like No Country for Old Men"}, {"score": 95.53, "title": "The Casebook of Sherlock Holmes viewers"}, {"score": 89.5, "title": "People who like Beef Stroganoff"}, {"score": 82.4, "title": "People who like H\u00e4agen-Dazs Chocolate and Pralines and Caramel Ice Cream"}, {"score": 93.57, "title": "People who like Haribo Giant Cola Bottles"}, {"score": 48.35, "title": "People who like He's Just Not That Into You"}, {"score": 47.71, "title": "People who like Hanna"}, {"score": 52.1, "title": "Readers of The Girl with the Dragon Tattoo"}, {"score": 75.25, "title": "Fans of The Secret of Monkey Island: Special Edition"}, {"score": 35.66, "title": "Fans of Harry Enfield"}, {"score": 97.53, "title": "People who like Joshua Reynolds"}, {"score": 63.45, "title": "People who like Walkers Crinkles Sea Salted"}]