[{"score": 61.99, "title": "Jeeves and Wooster viewers"}, {"score": 10.85, "title": "Viewers of HBO"}, {"score": 31.41, "title": "People who like David Lammy"}, {"score": 7.01, "title": "People who like Giant African Land Snails"}, {"score": 25.83, "title": "Fans of Brendan Gleeson"}, {"score": 83.06, "title": "Listeners of The World Today"}, {"score": 32.44, "title": "Fans of Mass Effect"}, {"score": 71.55, "title": "As Time Goes By viewers"}, {"score": 40.1, "title": "People who like Vizsla"}, {"score": 53.09, "title": "Customers of Amazon"}, {"score": 96.97, "title": "Fans of Dieterich Buxtehude"}, {"score": 71.97, "title": "People who like Tickled Pink"}, {"score": 73.65, "title": "Fans of Australia National Cricket Team"}, {"score": 27.59, "title": "People who enjoy Johnnie Walker Championship at Gleneagles"}, {"score": 56.79, "title": "Customers of Hotpoint"}, {"score": 98.25, "title": "People who like Shchi"}, {"score": 8.62, "title": "People who enjoy Winter Olympic Games"}, {"score": 51.77, "title": "People who like Martin Bell"}, {"score": 1.35, "title": "Fans of Wales National Rugby League Team"}, {"score": 77.73, "title": "Fans of Fulton Mackay"}, {"score": 82.79, "title": "Readers of David Icke"}, {"score": 52.67, "title": "Fans of Chris Froome"}, {"score": 20.7, "title": "People who like Glendronach"}, {"score": 52.36, "title": "Fans of Travis"}, {"score": 35.24, "title": "People who like Siu Mai"}, {"score": 27.92, "title": "People who like Jelly Belly Original"}, {"score": 95.08, "title": "People who like Prince of Persia: The Sands of Time"}, {"score": 33.33, "title": "Fans of Lena Dunham"}, {"score": 19.65, "title": "Fans of Mishal Husain"}, {"score": 16.22, "title": "People who own a HTC One"}, {"score": 35.34, "title": "Customers of FA Premier League"}, {"score": 11.4, "title": "People who like Crussh"}, {"score": 74.06, "title": "Fans of Del Shannon"}, {"score": 95.08, "title": "Readers of Dennis Wheatley"}, {"score": 13.04, "title": "Fans of Angel Coulby"}, {"score": 83.51, "title": "People who like Rockport"}, {"score": 70.06, "title": "People who like Honey, I Shrunk the Kids"}, {"score": 55.35, "title": "Fans of Steve Bruce"}, {"score": 65.45, "title": "People who enjoy Piano"}, {"score": 67.3, "title": "People who like Bringing up Baby"}, {"score": 49.73, "title": "Customers of Panasonic"}, {"score": 13.03, "title": "People who like Michael Connarty"}, {"score": 27.87, "title": "Readers of Ian Fleming"}, {"score": 67.07, "title": "People who buy things from Apple"}, {"score": 69.35, "title": "The 100 viewers"}, {"score": 57.05, "title": "People who like Royal College of Nursing (RCN)"}, {"score": 8.8, "title": "People who like Grenada"}, {"score": 5.59, "title": "Fans of Mischa Barton"}, {"score": 87.22, "title": "Fans of Bruce Parry"}, {"score": 80.86, "title": "People who like John Ruskin"}, {"score": 96.4, "title": "Fans of David Moorcroft"}, {"score": 75.82, "title": "Users of SatNav."}, {"score": 57.8, "title": "People who like Last Action Hero"}, {"score": 87.99, "title": "People who like Ben & Jerry's Coconutterly Fair Ice Cream"}, {"score": 82.15, "title": "People who like Bram Stoker's Dracula"}, {"score": 96.62, "title": "People who like Cadbury Crunchie Ice Cream"}, {"score": 49.92, "title": "People who like Scottish Smoked Salmon"}, {"score": 6.86, "title": "Fans of Julia Louis-Dreyfus"}, {"score": 5.43, "title": "Readers of BBC History Magazine"}, {"score": 82.27, "title": "People who like The Chronicles of Narnia: The Lion, the Witch and the Wardrobe"}, {"score": 32.67, "title": "Fans of Joy Division"}, {"score": 97.64, "title": "Fans of Orbital"}, {"score": 99.3, "title": "Fans of Henry McGee"}, {"score": 40.54, "title": "Fans of Wrexham A.F.C."}, {"score": 94.34, "title": "Al Murray: The Pub Landlord viewers"}, {"score": 79.58, "title": "British people who have a special interest in Afghanistan"}, {"score": 80.34, "title": "People who like Pygmalion"}, {"score": 18.64, "title": "Customers of Airwaves"}, {"score": 58.56, "title": "People who like OVD"}, {"score": 66.18, "title": "Fans of Ramones"}, {"score": 11.64, "title": "Wild Africa viewers"}, {"score": 34.41, "title": "People who wear Mango"}, {"score": 98.6, "title": "Fans of James Dreyfus"}, {"score": 8.01, "title": "People who like Oreo Double Stuff Cookies"}, {"score": 12.57, "title": "People who enjoy Jogging and running"}, {"score": 81.2, "title": "People who are interested in Immigration law"}, {"score": 48.28, "title": "Customers of Six Nations Championship"}, {"score": 13.57, "title": "People who like Saturday Night and Sunday Morning"}, {"score": 26.39, "title": "Listeners of The Motown Show"}, {"score": 8.47, "title": "Fans of Sophie Aldred"}, {"score": 81.82, "title": "Fans of Stanley Unwin"}, {"score": 4.92, "title": "People who like The Girl Who Played with Fire"}, {"score": 80.05, "title": "Beauty and the Beast viewers"}, {"score": 79.07, "title": "People who like Venison Pie"}, {"score": 4.09, "title": "Golden Balls viewers"}, {"score": 21.43, "title": "Users of Talking Tom Cat"}, {"score": 3.32, "title": "Readers of Different Seasons"}, {"score": 4.83, "title": "People who like Queen of the Damned"}, {"score": 66.16, "title": "Fans of Liam Plunkett"}, {"score": 21.24, "title": "People who like Pharaoh Hound"}, {"score": 39.46, "title": "People who describe themselves as Hesitant"}, {"score": 95.21, "title": "People who like Spicy Tuna Temaki"}, {"score": 60.22, "title": "Fans of Ola Jordan"}, {"score": 4.49, "title": "People who like Michael O'Leary"}, {"score": 24.69, "title": "People who like Georgia O'Keeffe"}, {"score": 61.81, "title": "Fans of Richard Griffiths"}, {"score": 75.0, "title": "Readers of Nigellissima: Instant Italian Inspiration"}, {"score": 18.97, "title": "People who use Pro plus"}, {"score": 14.42, "title": "People who like Legally Blonde"}, {"score": 25.64, "title": "Fans of Limahl"}, {"score": 2.61, "title": "People who like Moshulu"}, {"score": 74.46, "title": "People who like Association for International Cancer Research"}, {"score": 70.69, "title": "People who enjoy Christmas"}, {"score": 97.97, "title": "Fans of Milton Keynes Dons F.C."}, {"score": 64.88, "title": "Fans of World of Warcraft"}, {"score": 93.61, "title": "People who like Flapjack"}, {"score": 15.7, "title": "People who bank with Smile"}, {"score": 31.21, "title": "People who like Wheat Crunchies"}, {"score": 29.81, "title": "Fans of Patrick Stewart"}, {"score": 62.74, "title": "James May's Cars of the People viewers"}, {"score": 61.83, "title": "People who like The Matrix Reloaded"}, {"score": 43.82, "title": "People who like Ben & Jerry's Phish Food Frozen Yogurt"}, {"score": 3.27, "title": "People who like Tentoji Don"}, {"score": 10.22, "title": "People who like The Butterfly Effect"}, {"score": 0.81, "title": "People who like Mongol"}, {"score": 89.42, "title": "Fans of Robert Redford"}, {"score": 31.68, "title": "People who like Hop Stuff Brewery"}, {"score": 17.87, "title": "The Story of Musicals viewers"}, {"score": 25.19, "title": "People who like Iain Wright"}, {"score": 68.36, "title": "People who like Gettysburg"}]